sparkbar/__init__.py
sparkbar/sparkbar.py
sparkbar-1.0.2.dist-info/LICENSE
sparkbar-1.0.2.dist-info/METADATA
sparkbar-1.0.2.dist-info/WHEEL
sparkbar-1.0.2.dist-info/top_level.txt
sparkbar-1.0.2.dist-info/RECORD
